Scrapper.py
wscrapper-0.0.1.dist-info/licenses/LICENSE.txt
wscrapper-0.0.1.dist-info/METADATA
wscrapper-0.0.1.dist-info/WHEEL
wscrapper-0.0.1.dist-info/top_level.txt
wscrapper-0.0.1.dist-info/RECORD
